[
  {"name": "Everest Base Camp Trek", "country": "Nepal", "latitude": 27.9881, "longitude": 86.9250, "difficulty": "hard", "best_month_start": 3, "best_month_end": 5, "description": "Walk through Sherpa villages to the foot of the world's highest mountain. Life changing.", "distance_km": 130, "duration_days": 14, "popularity_score": 0.99, "terrain_type": "mountain", "is_offbeat": false},
  {"name": "Annapurna Circuit", "country": "Nepal", "latitude": 28.5971, "longitude": 83.8200, "difficulty": "hard", "best_month_start": 3, "best_month_end": 5, "description": "Circles the entire Annapurna massif crossing Thorong La pass at 5416m through diverse landscapes.", "distance_km": 160, "duration_days": 15, "popularity_score": 0.96, "terrain_type": "mountain", "is_offbeat": false},
  {"name": "Mardi Himal Trek", "country": "Nepal", "latitude": 28.3833, "longitude": 83.9667, "difficulty": "medium", "best_month_start": 3, "best_month_end": 5, "description": "Nepal's best kept secret with stunning Annapurna views and a fraction of the EBC crowds.", "distance_km": 55, "duration_days": 7, "popularity_score": 0.74, "terrain_type": "mountain", "is_offbeat": true},
  {"name": "Poon Hill Trek", "country": "Nepal", "latitude": 28.4000, "longitude": 83.6920, "difficulty": "easy", "best_month_start": 1, "best_month_end": 12, "description": "Most popular short trek in Nepal with stunning sunrise views over the Annapurna range.", "distance_km": 65, "duration_days": 4, "popularity_score": 0.92, "terrain_type": "mountain", "is_offbeat": false},
  {"name": "Langtang Valley Trek", "country": "Nepal", "latitude": 28.2121, "longitude": 85.5121, "difficulty": "medium", "best_month_start": 3, "best_month_end": 5, "description": "The valley of glaciers offers stunning Himalayan scenery with authentic Tamang culture.", "distance_km": 65, "duration_days": 7, "popularity_score": 0.82, "terrain_type": "mountain", "is_offbeat": false},
  {"name": "Upper Mustang Trek", "country": "Nepal", "latitude": 29.1833, "longitude": 83.9500, "difficulty": "hard", "best_month_start": 4, "best_month_end": 10, "description": "Trekking through the forbidden kingdom of Lo with ancient caves and Tibetan Buddhist culture.", "distance_km": 180, "duration_days": 16, "popularity_score": 0.78, "terrain_type": "desert", "is_offbeat": true},
  {"name": "Chadar Trek", "country": "India", "latitude": 33.7782, "longitude": 77.3411, "difficulty": "extreme", "best_month_start": 1, "best_month_end": 2, "description": "Walking on the frozen Zanskar River in Ladakh winter with temperatures dropping to -30C.", "distance_km": 105, "duration_days": 9, "popularity_score": 0.88, "terrain_type": "snow", "is_offbeat": false},
  {"name": "Valley of Flowers", "country": "India", "latitude": 30.7275, "longitude": 79.6081, "difficulty": "medium", "best_month_start": 7, "best_month_end": 9, "description": "UNESCO World Heritage valley in Uttarakhand bursts with hundreds of wildflower species during monsoon.", "distance_km": 38, "duration_days": 6, "popularity_score": 0.87, "terrain_type": "valley", "is_offbeat": false},
  {"name": "Kedarkantha Trek", "country": "India", "latitude": 31.0210, "longitude": 78.1948, "difficulty": "medium", "best_month_start": 12, "best_month_end": 3, "description": "India's best winter trek through dense snow-covered pine forests with panoramic Himalayan summit views.", "distance_km": 20, "duration_days": 6, "popularity_score": 0.85, "terrain_type": "snow", "is_offbeat": false},
  {"name": "Sandakphu Trek", "country": "India", "latitude": 27.1053, "longitude": 88.0009, "difficulty": "medium", "best_month_start": 4, "best_month_end": 5, "description": "The only place to see four of the world's five highest peaks simultaneously from West Bengal.", "distance_km": 51, "duration_days": 6, "popularity_score": 0.80, "terrain_type": "mountain", "is_offbeat": false},
  {"name": "Hampta Pass Trek", "country": "India", "latitude": 32.2526, "longitude": 77.4413, "difficulty": "medium", "best_month_start": 6, "best_month_end": 9, "description": "Dramatic crossover trek from green Kullu valley to barren Spiti landscape through a high mountain pass.", "distance_km": 35, "duration_days": 5, "popularity_score": 0.79, "terrain_type": "mountain", "is_offbeat": false},
  {"name": "Dzukou Valley Trek", "country": "India", "latitude": 25.5513, "longitude": 94.0833, "difficulty": "medium", "best_month_start": 6, "best_month_end": 9, "description": "Hidden valley on the Nagaland-Manipur border covered in seasonal flowers with almost no tourists.", "distance_km": 25, "duration_days": 3, "popularity_score": 0.68, "terrain_type": "valley", "is_offbeat": true},
  {"name": "Roopkund Trek", "country": "India", "latitude": 30.2500, "longitude": 79.7306, "difficulty": "hard", "best_month_start": 5, "best_month_end": 6, "description": "Trek to a mysterious glacial lake filled with ancient human skeletons at 5029m in Uttarakhand.", "distance_km": 53, "duration_days": 8, "popularity_score": 0.83, "terrain_type": "mountain", "is_offbeat": false},
  {"name": "Markha Valley Trek", "country": "India", "latitude": 33.8700, "longitude": 77.4400, "difficulty": "hard", "best_month_start": 6, "best_month_end": 9, "description": "Classic Ladakh trek through remote villages beneath Kang Yatze peak with stunning desert mountain scenery.", "distance_km": 80, "duration_days": 8, "popularity_score": 0.76, "terrain_type": "desert", "is_offbeat": false},
  {"name": "Pin Parvati Pass Trek", "country": "India", "latitude": 31.9667, "longitude": 77.8500, "difficulty": "extreme", "best_month_start": 7, "best_month_end": 8, "description": "One of India's most challenging crossover treks connecting green Parvati valley with barren Pin valley.", "distance_km": 110, "duration_days": 11, "popularity_score": 0.71, "terrain_type": "mountain", "is_offbeat": true},
  {"name": "Kheerganga Trek", "country": "India", "latitude": 32.1462, "longitude": 77.3322, "difficulty": "easy", "best_month_start": 5, "best_month_end": 10, "description": "Easy Himalayan trek ending at natural hot springs and camping meadows in Parvati Valley.", "distance_km": 22, "duration_days": 2, "popularity_score": 0.75, "terrain_type": "forest", "is_offbeat": false},
  {"name": "Inca Trail", "country": "Peru", "latitude": -13.1631, "longitude": -72.5450, "difficulty": "medium", "best_month_start": 4, "best_month_end": 10, "description": "Four-day archaeological trek through cloud forests ending at Machu Picchu at sunrise.", "distance_km": 43, "duration_days": 4, "popularity_score": 0.98, "terrain_type": "mountain", "is_offbeat": false},
  {"name": "Torres del Paine W Trek", "country": "Chile", "latitude": -50.9423, "longitude": -73.4068, "difficulty": "hard", "best_month_start": 11, "best_month_end": 3, "description": "Patagonia's most iconic trek past jagged granite towers and turquoise glacial lakes in howling winds.", "distance_km": 80, "duration_days": 5, "popularity_score": 0.95, "terrain_type": "mountain", "is_offbeat": false},
  {"name": "Laugavegur Trail", "country": "Iceland", "latitude": 63.9977, "longitude": -19.0522, "difficulty": "medium", "best_month_start": 7, "best_month_end": 8, "description": "Iceland's celebrated trek through lunar landscapes of colorful rhyolite mountains and geothermal areas.", "distance_km": 55, "duration_days": 4, "popularity_score": 0.89, "terrain_type": "mountain", "is_offbeat": false},
  {"name": "Milford Track", "country": "New Zealand", "latitude": -44.6731, "longitude": 167.9339, "difficulty": "medium", "best_month_start": 11, "best_month_end": 4, "description": "New Zealand's finest walk through ancient rainforests and dramatic fiordland to Milford Sound.", "distance_km": 54, "duration_days": 4, "popularity_score": 0.94, "terrain_type": "forest", "is_offbeat": false},
  {"name": "Tour du Mont Blanc", "country": "France", "latitude": 45.9237, "longitude": 6.8694, "difficulty": "hard", "best_month_start": 6, "best_month_end": 9, "description": "Legendary circuit around Mont Blanc through France, Italy and Switzerland with dramatic alpine scenery.", "distance_km": 170, "duration_days": 11, "popularity_score": 0.93, "terrain_type": "mountain", "is_offbeat": false},
  {"name": "GR20", "country": "France", "latitude": 42.1167, "longitude": 9.1500, "difficulty": "hard", "best_month_start": 6, "best_month_end": 9, "description": "Europe's toughest long-distance trail across Corsica's granite spine with wild camping and mountain refuges.", "distance_km": 180, "duration_days": 15, "popularity_score": 0.88, "terrain_type": "mountain", "is_offbeat": false},
  {"name": "Camino de Santiago", "country": "Spain", "latitude": 42.8782, "longitude": -8.5448, "difficulty": "easy", "best_month_start": 4, "best_month_end": 10, "description": "Ancient pilgrim route ending at Santiago de Compostela cathedral walking through Galician villages.", "distance_km": 800, "duration_days": 30, "popularity_score": 0.96, "terrain_type": "forest", "is_offbeat": false},
  {"name": "John Muir Trail", "country": "USA", "latitude": 37.7390, "longitude": -119.5960, "difficulty": "hard", "best_month_start": 7, "best_month_end": 9, "description": "Classic Sierra Nevada wilderness trail from Yosemite to Mount Whitney through breathtaking alpine terrain.", "distance_km": 340, "duration_days": 21, "popularity_score": 0.92, "terrain_type": "mountain", "is_offbeat": false},
  {"name": "Appalachian Trail", "country": "USA", "latitude": 34.6340, "longitude": -84.1920, "difficulty": "hard", "best_month_start": 3, "best_month_end": 10, "description": "Epic 2190-mile trail from Georgia to Maine through 14 states and America's eastern wilderness.", "distance_km": 3525, "duration_days": 180, "popularity_score": 0.91, "terrain_type": "forest", "is_offbeat": false},
  {"name": "Overland Track", "country": "Australia", "latitude": -42.0300, "longitude": 146.2500, "difficulty": "medium", "best_month_start": 10, "best_month_end": 5, "description": "Tasmania's premier wilderness walk through ancient rainforests, alpine meadows and dramatic dolerite peaks.", "distance_km": 65, "duration_days": 6, "popularity_score": 0.84, "terrain_type": "forest", "is_offbeat": false},
  {"name": "Kungsleden", "country": "Sweden", "latitude": 68.4200, "longitude": 18.5500, "difficulty": "medium", "best_month_start": 7, "best_month_end": 9, "description": "The King's Trail through Swedish Lapland's vast wilderness past Kebnekaise Sweden's highest peak.", "distance_km": 440, "duration_days": 28, "popularity_score": 0.79, "terrain_type": "mountain", "is_offbeat": false},
  {"name": "Kilimanjaro Marangu Route", "country": "Tanzania", "latitude": -3.0674, "longitude": 37.3556, "difficulty": "hard", "best_month_start": 1, "best_month_end": 12, "description": "The only route with hut accommodation up Africa's highest peak through five distinct climate zones.", "distance_km": 64, "duration_days": 6, "popularity_score": 0.97, "terrain_type": "mountain", "is_offbeat": false},
  {"name": "Simien Mountains Trek", "country": "Ethiopia", "latitude": 13.2400, "longitude": 38.0300, "difficulty": "medium", "best_month_start": 10, "best_month_end": 3, "description": "Dramatic highland plateau with Gelada baboons, Ethiopian wolves and views over ancient escarpments.", "distance_km": 100, "duration_days": 7, "popularity_score": 0.73, "terrain_type": "mountain", "is_offbeat": true},
  {"name": "Atlas Mountains Trek", "country": "Morocco", "latitude": 31.0606, "longitude": -7.9130, "difficulty": "medium", "best_month_start": 4, "best_month_end": 6, "description": "Trekking through Berber villages and walnut groves to Toubkal North Africa's highest peak at 4167m.", "distance_km": 55, "duration_days": 5, "popularity_score": 0.80, "terrain_type": "mountain", "is_offbeat": false},
  {"name": "Annapurna Base Camp Trek", "country": "Nepal", "latitude": 28.5308, "longitude": 83.8772, "difficulty": "medium", "best_month_start": 3, "best_month_end": 5, "description": "Trek to the base of Annapurna I through rhododendron forests and Gurung villages to a breathtaking amphitheatre.", "distance_km": 115, "duration_days": 10, "popularity_score": 0.94, "terrain_type": "mountain", "is_offbeat": false},
  {"name": "Gosaikunda Lake Trek", "country": "Nepal", "latitude": 28.0841, "longitude": 85.4163, "difficulty": "hard", "best_month_start": 9, "best_month_end": 11, "description": "Sacred Shiva lake at 4380m where Hindu pilgrims bathe during Janai Purnima festival each year.", "distance_km": 60, "duration_days": 5, "popularity_score": 0.72, "terrain_type": "mountain", "is_offbeat": true},
  {"name": "Stok Kangri Trek", "country": "India", "latitude": 34.0130, "longitude": 77.6000, "difficulty": "extreme", "best_month_start": 6, "best_month_end": 8, "description": "Summit trek to 6153m peak near Leh offering 360-degree views of the Ladakh and Zanskar ranges.", "distance_km": 40, "duration_days": 7, "popularity_score": 0.75, "terrain_type": "mountain", "is_offbeat": true},
  {"name": "Tarsar Marsar Trek", "country": "India", "latitude": 34.0500, "longitude": 75.3000, "difficulty": "medium", "best_month_start": 7, "best_month_end": 9, "description": "Hidden twin alpine lakes in Kashmir's Lidder valley surrounded by flower-filled meadows and pine forests.", "distance_km": 48, "duration_days": 6, "popularity_score": 0.70, "terrain_type": "mountain", "is_offbeat": true},
  {"name": "Kashmir Great Lakes Trek", "country": "India", "latitude": 34.3000, "longitude": 74.8000, "difficulty": "hard", "best_month_start": 7, "best_month_end": 9, "description": "Seven pristine alpine lakes connected by high mountain passes in the most beautiful trek in Kashmir.", "distance_km": 70, "duration_days": 7, "popularity_score": 0.82, "terrain_type": "mountain", "is_offbeat": false},
  {"name": "Brahmatal Trek", "country": "India", "latitude": 30.1700, "longitude": 79.5100, "difficulty": "medium", "best_month_start": 12, "best_month_end": 2, "description": "Winter high-altitude trek with stunning frozen lake and panoramic views of Trishul and Nanda Ghunti.", "distance_km": 22, "duration_days": 6, "popularity_score": 0.71, "terrain_type": "snow", "is_offbeat": true},
  {"name": "Kuari Pass Trek", "country": "India", "latitude": 30.5500, "longitude": 79.6900, "difficulty": "medium", "best_month_start": 4, "best_month_end": 6, "description": "Lord Curzon's trail offering stunning views of Nanda Devi and other Garhwal Himalayan peaks.", "distance_km": 35, "duration_days": 5, "popularity_score": 0.73, "terrain_type": "mountain", "is_offbeat": false},
  {"name": "Dayara Bugyal Trek", "country": "India", "latitude": 31.0600, "longitude": 78.4200, "difficulty": "easy", "best_month_start": 10, "best_month_end": 12, "description": "India's finest high-altitude meadow turns into a snow wonderland perfect for beginners in winter.", "distance_km": 22, "duration_days": 4, "popularity_score": 0.68, "terrain_type": "snow", "is_offbeat": true},
  {"name": "Har Ki Dun Trek", "country": "India", "latitude": 31.1500, "longitude": 78.4000, "difficulty": "medium", "best_month_start": 4, "best_month_end": 6, "description": "Cradle of civilization trek to a valley mentioned in the Mahabharata with ancient wooden temples.", "distance_km": 50, "duration_days": 7, "popularity_score": 0.76, "terrain_type": "valley", "is_offbeat": false},
  {"name": "Rupin Pass Trek", "country": "India", "latitude": 31.3600, "longitude": 78.1300, "difficulty": "hard", "best_month_start": 5, "best_month_end": 6, "description": "Spectacular trek with a dramatic frozen waterfall crossing at the Rupin Pass at 4650m.", "distance_km": 52, "duration_days": 8, "popularity_score": 0.77, "terrain_type": "mountain", "is_offbeat": false},
  {"name": "Patagonia Circuit Trek", "country": "Argentina", "latitude": -49.5000, "longitude": -73.4000, "difficulty": "extreme", "best_month_start": 11, "best_month_end": 3, "description": "Remote circuit around Torres del Paine visiting glaciers and valleys inaccessible by any other means.", "distance_km": 130, "duration_days": 10, "popularity_score": 0.81, "terrain_type": "mountain", "is_offbeat": true},
  {"name": "Huayhuash Circuit", "country": "Peru", "latitude": -10.2500, "longitude": -76.9000, "difficulty": "extreme", "best_month_start": 5, "best_month_end": 9, "description": "Remote Peruvian circuit past turquoise lakes and glaciated peaks in arguably the world's most beautiful trek.", "distance_km": 130, "duration_days": 12, "popularity_score": 0.86, "terrain_type": "mountain", "is_offbeat": true},
  {"name": "Mount Rinjani Trek", "country": "Indonesia", "latitude": -8.4142, "longitude": 116.4675, "difficulty": "hard", "best_month_start": 4, "best_month_end": 8, "description": "Volcano summit trek in Lombok with crater lake and stunning views across to Bali and Sumbawa.", "distance_km": 35, "duration_days": 3, "popularity_score": 0.83, "terrain_type": "mountain", "is_offbeat": false},
  {"name": "Adam's Peak Trek", "country": "Sri Lanka", "latitude": 6.8096, "longitude": 80.4994, "difficulty": "medium", "best_month_start": 12, "best_month_end": 4, "description": "Night trek to Sri Lanka's sacred footprint summit to witness one of the world's most stunning sunrises.", "distance_km": 14, "duration_days": 1, "popularity_score": 0.79, "terrain_type": "mountain", "is_offbeat": false},
  {"name": "Annapurna Sanctuary Trek", "country": "Nepal", "latitude": 28.5308, "longitude": 83.8772, "difficulty": "medium", "best_month_start": 9, "best_month_end": 11, "description": "Autumn trek into the natural amphitheatre surrounded by 360 degrees of 7000m Himalayan peaks.", "distance_km": 115, "duration_days": 10, "popularity_score": 0.91, "terrain_type": "mountain", "is_offbeat": false},
  {"name": "Snowman Trek", "country": "Bhutan", "latitude": 28.2180, "longitude": 90.7340, "difficulty": "extreme", "best_month_start": 9, "best_month_end": 10, "description": "The world's hardest trek crossing 11 passes above 4000m through Bhutan's remote northern highlands.", "distance_km": 380, "duration_days": 25, "popularity_score": 0.65, "terrain_type": "mountain", "is_offbeat": true},
  {"name": "Markha Valley to Nimaling", "country": "India", "latitude": 33.9000, "longitude": 77.6200, "difficulty": "hard", "best_month_start": 7, "best_month_end": 9, "description": "Extended Ladakh trek through remote villages to the high meadow of Nimaling beneath Kang Yatse.", "distance_km": 100, "duration_days": 10, "popularity_score": 0.69, "terrain_type": "desert", "is_offbeat": true},
  {"name": "Miyar Valley Trek", "country": "India", "latitude": 33.0500, "longitude": 76.7700, "difficulty": "hard", "best_month_start": 7, "best_month_end": 9, "description": "Remote Himachal Pradesh valley trek to the Chhudong glacier with pristine wilderness and no crowds.", "distance_km": 80, "duration_days": 9, "popularity_score": 0.58, "terrain_type": "mountain", "is_offbeat": true},
  {"name": "Zanskar Valley Trek", "country": "India", "latitude": 33.5167, "longitude": 76.7667, "difficulty": "hard", "best_month_start": 7, "best_month_end": 9, "description": "Remote high-altitude valley trek with ancient monasteries, turquoise rivers and dramatic gorges.", "distance_km": 200, "duration_days": 18, "popularity_score": 0.72, "terrain_type": "mountain", "is_offbeat": true},
  {"name": "Satopanth Lake Trek", "country": "India", "latitude": 30.8800, "longitude": 79.4400, "difficulty": "hard", "best_month_start": 5, "best_month_end": 6, "description": "Sacred Himalayan lake at 4600m associated with Hindu trinity with stunning views of glaciated peaks.", "distance_km": 40, "duration_days": 7, "popularity_score": 0.64, "terrain_type": "mountain", "is_offbeat": true},
  {"name": "Singalila Ridge Trek", "country": "India", "latitude": 27.0700, "longitude": 88.0600, "difficulty": "medium", "best_month_start": 4, "best_month_end": 5, "description": "Forested ridge walk on the India-Nepal border with views of four 8000m peaks including Everest and Kangchenjunga.", "distance_km": 60, "duration_days": 5, "popularity_score": 0.74, "terrain_type": "forest", "is_offbeat": false},
  {"name": "Chembra Peak Trek", "country": "India", "latitude": 11.5100, "longitude": 76.0500, "difficulty": "medium", "best_month_start": 10, "best_month_end": 2, "description": "Heart-shaped lake trek in Kerala's Wayanad hills with views over the Western Ghats tea estates.", "distance_km": 12, "duration_days": 1, "popularity_score": 0.70, "terrain_type": "forest", "is_offbeat": false},
  {"name": "Meesapulimala Trek", "country": "India", "latitude": 10.0600, "longitude": 77.2000, "difficulty": "hard", "best_month_start": 12, "best_month_end": 2, "description": "Kerala's second highest peak through shola forests and grasslands with rare Nilgiri Tahr sightings.", "distance_km": 25, "duration_days": 2, "popularity_score": 0.62, "terrain_type": "forest", "is_offbeat": true},
  {"name": "Kumara Parvatha Trek", "country": "India", "latitude": 12.6400, "longitude": 75.7800, "difficulty": "hard", "best_month_start": 10, "best_month_end": 2, "description": "Challenging Western Ghats summit trek through dense Pushpagiri forests with panoramic coastal views.", "distance_km": 26, "duration_days": 2, "popularity_score": 0.67, "terrain_type": "forest", "is_offbeat": false},
  {"name": "Kodachadri Trek", "country": "India", "latitude": 13.9700, "longitude": 74.9700, "difficulty": "medium", "best_month_start": 10, "best_month_end": 2, "description": "Western Ghats peak trek through pristine forests to a temple summit with sunset views over the Arabian Sea.", "distance_km": 20, "duration_days": 2, "popularity_score": 0.65, "terrain_type": "forest", "is_offbeat": true},
  {"name": "Bibbulmun Track", "country": "Australia", "latitude": -31.9505, "longitude": 115.8605, "difficulty": "hard", "best_month_start": 4, "best_month_end": 11, "description": "Epic 1000km trail through Western Australia's diverse landscapes from Perth to Albany.", "distance_km": 1000, "duration_days": 60, "popularity_score": 0.75, "terrain_type": "forest", "is_offbeat": true},
  {"name": "Tongariro Alpine Crossing", "country": "New Zealand", "latitude": -39.2000, "longitude": 175.5700, "difficulty": "medium", "best_month_start": 11, "best_month_end": 4, "description": "New Zealand's most popular day walk past active volcanoes, emerald lakes and lunar landscapes.", "distance_km": 20, "duration_days": 1, "popularity_score": 0.93, "terrain_type": "mountain", "is_offbeat": false},
  {"name": "Routeburn Track", "country": "New Zealand", "latitude": -44.7400, "longitude": 168.1300, "difficulty": "medium", "best_month_start": 11, "best_month_end": 4, "description": "Multi-day alpine track through two national parks with stunning lake and mountain panoramas.", "distance_km": 32, "duration_days": 3, "popularity_score": 0.88, "terrain_type": "mountain", "is_offbeat": false},
  {"name": "West Highland Way", "country": "UK", "latitude": 55.8642, "longitude": -4.2518, "difficulty": "medium", "best_month_start": 5, "best_month_end": 9, "description": "Scotland's classic long-distance walk from Glasgow through highland lochs and glens to Fort William.", "distance_km": 154, "duration_days": 7, "popularity_score": 0.87, "terrain_type": "mountain", "is_offbeat": false},
  {"name": "Haute Route", "country": "France", "latitude": 45.9740, "longitude": 7.1900, "difficulty": "hard", "best_month_start": 7, "best_month_end": 9, "description": "Classic Alpine traverse from Chamonix to Zermatt crossing remote high mountain passes above 3000m.", "distance_km": 200, "duration_days": 14, "popularity_score": 0.87, "terrain_type": "mountain", "is_offbeat": false},
  {"name": "Dolomites Alta Via 1", "country": "Italy", "latitude": 46.5963, "longitude": 12.1967, "difficulty": "medium", "best_month_start": 7, "best_month_end": 9, "description": "Classic high route through Italy's UNESCO-listed Dolomites with dramatic rock towers and alpine huts.", "distance_km": 120, "duration_days": 10, "popularity_score": 0.89, "terrain_type": "mountain", "is_offbeat": false},
  {"name": "Fimmvorduhals Trek", "country": "Iceland", "latitude": 63.6600, "longitude": -19.5700, "difficulty": "hard", "best_month_start": 6, "best_month_end": 8, "description": "Challenging Icelandic trek past the 2010 volcanic eruption site connecting two iconic Icelandic trails.", "distance_km": 25, "duration_days": 1, "popularity_score": 0.73, "terrain_type": "mountain", "is_offbeat": true},
  {"name": "Kangchenjunga Base Camp Trek", "country": "Nepal", "latitude": 27.7025, "longitude": 88.1475, "difficulty": "hard", "best_month_start": 4, "best_month_end": 5, "description": "Remote eastern Nepal trek to the base of the world's third highest mountain through pristine wilderness.", "distance_km": 210, "duration_days": 20, "popularity_score": 0.70, "terrain_type": "mountain", "is_offbeat": true},
  {"name": "Dolpo Trek", "country": "Nepal", "latitude": 29.0000, "longitude": 82.8333, "difficulty": "extreme", "best_month_start": 9, "best_month_end": 10, "description": "Remote Himalayan wilderness trek into the hidden land of Dolpo featured in Peter Matthiessen's Snow Leopard.", "distance_km": 250, "duration_days": 22, "popularity_score": 0.63, "terrain_type": "mountain", "is_offbeat": true},
  {"name": "Dzongri Trek", "country": "India", "latitude": 27.5600, "longitude": 88.3300, "difficulty": "hard", "best_month_start": 4, "best_month_end": 5, "description": "Sikkim's most popular trek with rhododendron forests and stunning views of Kangchenjunga.", "distance_km": 60, "duration_days": 8, "popularity_score": 0.77, "terrain_type": "mountain", "is_offbeat": false},
  {"name": "Goecha La Trek", "country": "India", "latitude": 27.5200, "longitude": 88.3500, "difficulty": "extreme", "best_month_start": 4, "best_month_end": 5, "description": "Sikkim's ultimate trek to the viewpoint of Kangchenjunga's south face at 4940m.", "distance_km": 90, "duration_days": 11, "popularity_score": 0.75, "terrain_type": "mountain", "is_offbeat": true},
  {"name": "Nanda Devi Base Camp", "country": "India", "latitude": 30.3769, "longitude": 79.9907, "difficulty": "extreme", "best_month_start": 5, "best_month_end": 6, "description": "Trek into the Nanda Devi Sanctuary biosphere reserve surrounding India's second highest peak.", "distance_km": 70, "duration_days": 14, "popularity_score": 0.66, "terrain_type": "mountain", "is_offbeat": true},
  {"name": "Nagarkot Sunrise Trek", "country": "Nepal", "latitude": 27.7161, "longitude": 85.5188, "difficulty": "easy", "best_month_start": 10, "best_month_end": 4, "description": "Easy one-day trek near Kathmandu with stunning sunrise views of the entire Himalayan range.", "distance_km": 15, "duration_days": 2, "popularity_score": 0.79, "terrain_type": "mountain", "is_offbeat": false},
  {"name": "Kumano Kodo Pilgrimage", "country": "Japan", "latitude": 33.8342, "longitude": 135.7683, "difficulty": "medium", "best_month_start": 3, "best_month_end": 5, "description": "Ancient Japanese pilgrimage routes through Wakayama's sacred forests to three grand shrines.", "distance_km": 70, "duration_days": 5, "popularity_score": 0.82, "terrain_type": "forest", "is_offbeat": false},
  {"name": "Tiger's Nest Hike", "country": "Bhutan", "latitude": 27.4894, "longitude": 89.3616, "difficulty": "medium", "best_month_start": 3, "best_month_end": 5, "description": "Bhutan's iconic hike to the monastery perched on a 900m cliff face above the Paro Valley.", "distance_km": 10, "duration_days": 1, "popularity_score": 0.95, "terrain_type": "mountain", "is_offbeat": false},
  {"name": "Salkantay Trek", "country": "Peru", "latitude": -13.3389, "longitude": -72.7158, "difficulty": "hard", "best_month_start": 5, "best_month_end": 9, "description": "Alternative route to Machu Picchu past the sacred Salkantay glacier at 4600m through cloud forest.", "distance_km": 74, "duration_days": 5, "popularity_score": 0.85, "terrain_type": "mountain", "is_offbeat": false},
  {"name": "Drakensberg Amphitheatre", "country": "South Africa", "latitude": -28.7564, "longitude": 28.9264, "difficulty": "hard", "best_month_start": 9, "best_month_end": 4, "description": "Chain ladder ascent to one of the world's largest cliff faces with views of the Tugela waterfall.", "distance_km": 12, "duration_days": 1, "popularity_score": 0.78, "terrain_type": "mountain", "is_offbeat": true},
  {"name": "Rwenzori Mountains Trek", "country": "Uganda", "latitude": 0.3722, "longitude": 29.8939, "difficulty": "extreme", "best_month_start": 1, "best_month_end": 2, "description": "Trek through the legendary Mountains of the Moon past glaciers and giant lobelias to Margherita Peak.", "distance_km": 80, "duration_days": 8, "popularity_score": 0.65, "terrain_type": "mountain", "is_offbeat": true},
  {"name": "Fansipan Trek", "country": "Vietnam", "latitude": 22.3033, "longitude": 103.7761, "difficulty": "hard", "best_month_start": 9, "best_month_end": 11, "description": "Trek to the Roof of Indochina at 3143m through Hoang Lien Son mountain forest near Sapa.", "distance_km": 19, "duration_days": 3, "popularity_score": 0.74, "terrain_type": "mountain", "is_offbeat": false},
  {"name": "Volcan Acatenango Trek", "country": "Guatemala", "latitude": 14.5006, "longitude": -90.8759, "difficulty": "hard", "best_month_start": 11, "best_month_end": 4, "description": "Overnight trek to camp near the summit watching active Volcan de Fuego erupt just 4km away.", "distance_km": 16, "duration_days": 2, "popularity_score": 0.80, "terrain_type": "mountain", "is_offbeat": false},
  {"name": "Hallasan Crater Trek", "country": "South Korea", "latitude": 33.3617, "longitude": 126.5292, "difficulty": "medium", "best_month_start": 4, "best_month_end": 6, "description": "Day trek to South Korea's highest peak and crater lake on Jeju Island through azalea meadows.", "distance_km": 19, "duration_days": 1, "popularity_score": 0.76, "terrain_type": "mountain", "is_offbeat": false},
  {"name": "Deosai Plains Trek", "country": "Pakistan", "latitude": 35.2167, "longitude": 75.6000, "difficulty": "medium", "best_month_start": 7, "best_month_end": 9, "description": "Trekking the world's second highest plateau at 4114m with Himalayan brown bears and wildflowers.", "distance_km": 60, "duration_days": 4, "popularity_score": 0.67, "terrain_type": "mountain", "is_offbeat": true}
]
